<annotation>
	<folder>dv13_aps</folder>
	<filename>dv13-0730.bmp</filename>
	<path>F:\data\dv13-132\dv13_aps\dv13-0730.bmp</path>
	<source>
		<database>Unknown</database>
	</source>
	<size>
		<width>346</width>
		<height>260</height>
		<depth>3</depth>
	</size>
	<segmented>0</segmented>
	<object>
		<name>red belly glassfish</name>
		<pose>Unspecified</pose>
		<truncated>0</truncated>
		<difficult>0</difficult>
		<bndbox>
			<xmin>54</xmin>
			<ymin>18</ymin>
			<xmax>103</xmax>
			<ymax>33</ymax>
		</bndbox>
	</object>
	<object>
		<name>X-ray fish</name>
		<pose>Unspecified</pose>
		<truncated>0</truncated>
		<difficult>0</difficult>
		<bndbox>
			<xmin>43</xmin>
			<ymin>41</ymin>
			<xmax>94</xmax>
			<ymax>81</ymax>
		</bndbox>
	</object>
	<object>
		<name>red belly glassfish</name>
		<pose>Unspecified</pose>
		<truncated>0</truncated>
		<difficult>0</difficult>
		<bndbox>
			<xmin>267</xmin>
			<ymin>48</ymin>
			<xmax>304</xmax>
			<ymax>66</ymax>
		</bndbox>
	</object>
</annotation>
