<annotation>
	<folder>dv14_aps</folder>
	<filename>dv14-0095.bmp</filename>
	<path>F:\data\dv14-108\dv14_aps\dv14-0095.bmp</path>
	<source>
		<database>Unknown</database>
	</source>
	<size>
		<width>346</width>
		<height>260</height>
		<depth>3</depth>
	</size>
	<segmented>0</segmented>
	<object>
		<name>X-ray fish</name>
		<pose>Unspecified</pose>
		<truncated>1</truncated>
		<difficult>0</difficult>
		<bndbox>
			<xmin>1</xmin>
			<ymin>111</ymin>
			<xmax>21</xmax>
			<ymax>139</ymax>
		</bndbox>
	</object>
	<object>
		<name>redtail glassfish</name>
		<pose>Unspecified</pose>
		<truncated>0</truncated>
		<difficult>0</difficult>
		<bndbox>
			<xmin>113</xmin>
			<ymin>104</ymin>
			<xmax>227</xmax>
			<ymax>143</ymax>
		</bndbox>
	</object>
	<object>
		<name>X-ray fish</name>
		<pose>Unspecified</pose>
		<truncated>0</truncated>
		<difficult>0</difficult>
		<bndbox>
			<xmin>184</xmin>
			<ymin>143</ymin>
			<xmax>264</xmax>
			<ymax>194</ymax>
		</bndbox>
	</object>
	<object>
		<name>X-ray fish</name>
		<pose>Unspecified</pose>
		<truncated>0</truncated>
		<difficult>0</difficult>
		<bndbox>
			<xmin>116</xmin>
			<ymin>138</ymin>
			<xmax>149</xmax>
			<ymax>186</ymax>
		</bndbox>
	</object>
	<object>
		<name>red belly glassfish</name>
		<pose>Unspecified</pose>
		<truncated>0</truncated>
		<difficult>0</difficult>
		<bndbox>
			<xmin>180</xmin>
			<ymin>6</ymin>
			<xmax>202</xmax>
			<ymax>29</ymax>
		</bndbox>
	</object>
	<object>
		<name>red belly glassfish</name>
		<pose>Unspecified</pose>
		<truncated>0</truncated>
		<difficult>0</difficult>
		<bndbox>
			<xmin>261</xmin>
			<ymin>6</ymin>
			<xmax>279</xmax>
			<ymax>30</ymax>
		</bndbox>
	</object>
</annotation>
