<annotation>
	<folder>dv19_aps</folder>
	<filename>dv19-0100.bmp</filename>
	<path>F:\data\dv19-84\dv19_aps\dv19-0100.bmp</path>
	<source>
		<database>Unknown</database>
	</source>
	<size>
		<width>346</width>
		<height>260</height>
		<depth>3</depth>
	</size>
	<segmented>0</segmented>
	<object>
		<name>redtail glassfish</name>
		<pose>Unspecified</pose>
		<truncated>0</truncated>
		<difficult>0</difficult>
		<bndbox>
			<xmin>114</xmin>
			<ymin>31</ymin>
			<xmax>201</xmax>
			<ymax>67</ymax>
		</bndbox>
	</object>
	<object>
		<name>redtail glassfish</name>
		<pose>Unspecified</pose>
		<truncated>0</truncated>
		<difficult>0</difficult>
		<bndbox>
			<xmin>2</xmin>
			<ymin>17</ymin>
			<xmax>68</xmax>
			<ymax>42</ymax>
		</bndbox>
	</object>
	<object>
		<name>red belly glassfish</name>
		<pose>Unspecified</pose>
		<truncated>0</truncated>
		<difficult>0</difficult>
		<bndbox>
			<xmin>90</xmin>
			<ymin>70</ymin>
			<xmax>140</xmax>
			<ymax>88</ymax>
		</bndbox>
	</object>
	<object>
		<name>red belly glassfish</name>
		<pose>Unspecified</pose>
		<truncated>0</truncated>
		<difficult>0</difficult>
		<bndbox>
			<xmin>329</xmin>
			<ymin>60</ymin>
			<xmax>343</xmax>
			<ymax>81</ymax>
		</bndbox>
	</object>
</annotation>
