<annotation>
	<folder>dv24_aps</folder>
	<filename>dv24-0005.bmp</filename>
	<path>F:\data\dv24-110\dv24_aps\dv24-0005.bmp</path>
	<source>
		<database>Unknown</database>
	</source>
	<size>
		<width>346</width>
		<height>260</height>
		<depth>3</depth>
	</size>
	<segmented>0</segmented>
	<object>
		<name>redtail glassfish</name>
		<pose>Unspecified</pose>
		<truncated>0</truncated>
		<difficult>0</difficult>
		<bndbox>
			<xmin>81</xmin>
			<ymin>16</ymin>
			<xmax>171</xmax>
			<ymax>51</ymax>
		</bndbox>
	</object>
	<object>
		<name>redtail glassfish</name>
		<pose>Unspecified</pose>
		<truncated>0</truncated>
		<difficult>0</difficult>
		<bndbox>
			<xmin>119</xmin>
			<ymin>67</ymin>
			<xmax>198</xmax>
			<ymax>98</ymax>
		</bndbox>
	</object>
	<object>
		<name>glassfish</name>
		<pose>Unspecified</pose>
		<truncated>0</truncated>
		<difficult>0</difficult>
		<bndbox>
			<xmin>103</xmin>
			<ymin>176</ymin>
			<xmax>171</xmax>
			<ymax>202</ymax>
		</bndbox>
	</object>
	<object>
		<name>glassfish</name>
		<pose>Unspecified</pose>
		<truncated>0</truncated>
		<difficult>0</difficult>
		<bndbox>
			<xmin>201</xmin>
			<ymin>90</ymin>
			<xmax>311</xmax>
			<ymax>160</ymax>
		</bndbox>
	</object>
	<object>
		<name>red belly glassfish</name>
		<pose>Unspecified</pose>
		<truncated>1</truncated>
		<difficult>0</difficult>
		<bndbox>
			<xmin>332</xmin>
			<ymin>60</ymin>
			<xmax>346</xmax>
			<ymax>75</ymax>
		</bndbox>
	</object>
</annotation>
