<annotation>
	<folder>dv26_aps</folder>
	<filename>dv26-1010.bmp</filename>
	<path>D:\数据集标注\dv26\dv26_aps\dv26-1010.bmp</path>
	<source>
		<database>Unknown</database>
	</source>
	<size>
		<width>346</width>
		<height>260</height>
		<depth>3</depth>
	</size>
	<segmented>0</segmented>
	<object>
		<name>glassfish</name>
		<pose>Unspecified</pose>
		<truncated>1</truncated>
		<difficult>0</difficult>
		<bndbox>
			<xmin>72</xmin>
			<ymin>166</ymin>
			<xmax>130</xmax>
			<ymax>260</ymax>
		</bndbox>
	</object>
	<object>
		<name>glassfish</name>
		<pose>Unspecified</pose>
		<truncated>0</truncated>
		<difficult>0</difficult>
		<bndbox>
			<xmin>100</xmin>
			<ymin>118</ymin>
			<xmax>223</xmax>
			<ymax>171</ymax>
		</bndbox>
	</object>
	<object>
		<name>red belly glassfish</name>
		<pose>Unspecified</pose>
		<truncated>0</truncated>
		<difficult>0</difficult>
		<bndbox>
			<xmin>294</xmin>
			<ymin>40</ymin>
			<xmax>340</xmax>
			<ymax>58</ymax>
		</bndbox>
	</object>
	<object>
		<name>X-ray fish</name>
		<pose>Unspecified</pose>
		<truncated>0</truncated>
		<difficult>0</difficult>
		<bndbox>
			<xmin>67</xmin>
			<ymin>197</ymin>
			<xmax>91</xmax>
			<ymax>225</ymax>
		</bndbox>
	</object>
</annotation>
