<annotation>
	<folder>dv28_aps</folder>
	<filename>dv28-0285.bmp</filename>
	<path>C:\Users\86198\Documents\Tencent Files\2384866429\FileRecv\dv28-167\dv28_aps\dv28-0285.bmp</path>
	<source>
		<database>Unknown</database>
	</source>
	<size>
		<width>346</width>
		<height>260</height>
		<depth>3</depth>
	</size>
	<segmented>0</segmented>
	<object>
		<name>redtail glassfish</name>
		<pose>Unspecified</pose>
		<truncated>0</truncated>
		<difficult>0</difficult>
		<bndbox>
			<xmin>134</xmin>
			<ymin>99</ymin>
			<xmax>238</xmax>
			<ymax>123</ymax>
		</bndbox>
	</object>
	<object>
		<name>redtail glassfish</name>
		<pose>Unspecified</pose>
		<truncated>0</truncated>
		<difficult>0</difficult>
		<bndbox>
			<xmin>232</xmin>
			<ymin>89</ymin>
			<xmax>262</xmax>
			<ymax>112</ymax>
		</bndbox>
	</object>
	<object>
		<name>X-ray fish</name>
		<pose>Unspecified</pose>
		<truncated>1</truncated>
		<difficult>0</difficult>
		<bndbox>
			<xmin>329</xmin>
			<ymin>158</ymin>
			<xmax>346</xmax>
			<ymax>186</ymax>
		</bndbox>
	</object>
	<object>
		<name>red belly glassfish</name>
		<pose>Unspecified</pose>
		<truncated>0</truncated>
		<difficult>0</difficult>
		<bndbox>
			<xmin>287</xmin>
			<ymin>49</ymin>
			<xmax>314</xmax>
			<ymax>64</ymax>
		</bndbox>
	</object>
	<object>
		<name>red belly glassfish</name>
		<pose>Unspecified</pose>
		<truncated>1</truncated>
		<difficult>0</difficult>
		<bndbox>
			<xmin>314</xmin>
			<ymin>1</ymin>
			<xmax>346</xmax>
			<ymax>14</ymax>
		</bndbox>
	</object>
	<object>
		<name>red belly glassfish</name>
		<pose>Unspecified</pose>
		<truncated>0</truncated>
		<difficult>0</difficult>
		<bndbox>
			<xmin>27</xmin>
			<ymin>36</ymin>
			<xmax>63</xmax>
			<ymax>54</ymax>
		</bndbox>
	</object>
	<object>
		<name>redtail glassfish</name>
		<pose>Unspecified</pose>
		<truncated>0</truncated>
		<difficult>0</difficult>
		<bndbox>
			<xmin>10</xmin>
			<ymin>89</ymin>
			<xmax>56</xmax>
			<ymax>105</ymax>
		</bndbox>
	</object>
</annotation>
