<annotation>
	<folder>dv28_aps</folder>
	<filename>dv28-1400.bmp</filename>
	<path>C:\Users\86198\Documents\Tencent Files\2384866429\FileRecv\dv28-167\dv28_aps\dv28-1400.bmp</path>
	<source>
		<database>Unknown</database>
	</source>
	<size>
		<width>346</width>
		<height>260</height>
		<depth>3</depth>
	</size>
	<segmented>0</segmented>
	<object>
		<name>red belly glassfish</name>
		<pose>Unspecified</pose>
		<truncated>0</truncated>
		<difficult>0</difficult>
		<bndbox>
			<xmin>57</xmin>
			<ymin>34</ymin>
			<xmax>99</xmax>
			<ymax>53</ymax>
		</bndbox>
	</object>
	<object>
		<name>red belly glassfish</name>
		<pose>Unspecified</pose>
		<truncated>0</truncated>
		<difficult>0</difficult>
		<bndbox>
			<xmin>260</xmin>
			<ymin>67</ymin>
			<xmax>303</xmax>
			<ymax>90</ymax>
		</bndbox>
	</object>
	<object>
		<name>redtail glassfish</name>
		<pose>Unspecified</pose>
		<truncated>0</truncated>
		<difficult>0</difficult>
		<bndbox>
			<xmin>134</xmin>
			<ymin>73</ymin>
			<xmax>187</xmax>
			<ymax>103</ymax>
		</bndbox>
	</object>
	<object>
		<name>redtail glassfish</name>
		<pose>Unspecified</pose>
		<truncated>0</truncated>
		<difficult>0</difficult>
		<bndbox>
			<xmin>221</xmin>
			<ymin>94</ymin>
			<xmax>291</xmax>
			<ymax>136</ymax>
		</bndbox>
	</object>
	<object>
		<name>redtail glassfish</name>
		<pose>Unspecified</pose>
		<truncated>0</truncated>
		<difficult>0</difficult>
		<bndbox>
			<xmin>288</xmin>
			<ymin>177</ymin>
			<xmax>307</xmax>
			<ymax>201</ymax>
		</bndbox>
	</object>
	<object>
		<name>glassfish</name>
		<pose>Unspecified</pose>
		<truncated>1</truncated>
		<difficult>0</difficult>
		<bndbox>
			<xmin>319</xmin>
			<ymin>189</ymin>
			<xmax>346</xmax>
			<ymax>208</ymax>
		</bndbox>
	</object>
</annotation>
