<annotation>
	<folder>dv35_aps</folder>
	<filename>dv35-0250.bmp</filename>
	<path>F:\data\dv35-144\dv35_aps\dv35-0250.bmp</path>
	<source>
		<database>Unknown</database>
	</source>
	<size>
		<width>346</width>
		<height>260</height>
		<depth>3</depth>
	</size>
	<segmented>0</segmented>
	<object>
		<name>redtail glassfish</name>
		<pose>Unspecified</pose>
		<truncated>0</truncated>
		<difficult>0</difficult>
		<bndbox>
			<xmin>45</xmin>
			<ymin>34</ymin>
			<xmax>106</xmax>
			<ymax>60</ymax>
		</bndbox>
	</object>
	<object>
		<name>redtail glassfish</name>
		<pose>Unspecified</pose>
		<truncated>1</truncated>
		<difficult>0</difficult>
		<bndbox>
			<xmin>1</xmin>
			<ymin>28</ymin>
			<xmax>16</xmax>
			<ymax>45</ymax>
		</bndbox>
	</object>
	<object>
		<name>red belly glassfish</name>
		<pose>Unspecified</pose>
		<truncated>0</truncated>
		<difficult>0</difficult>
		<bndbox>
			<xmin>254</xmin>
			<ymin>31</ymin>
			<xmax>283</xmax>
			<ymax>46</ymax>
		</bndbox>
	</object>
	<object>
		<name>siberian prawn</name>
		<pose>Unspecified</pose>
		<truncated>0</truncated>
		<difficult>0</difficult>
		<bndbox>
			<xmin>176</xmin>
			<ymin>156</ymin>
			<xmax>237</xmax>
			<ymax>232</ymax>
		</bndbox>
	</object>
	<object>
		<name>redtail glassfish</name>
		<pose>Unspecified</pose>
		<truncated>0</truncated>
		<difficult>0</difficult>
		<bndbox>
			<xmin>324</xmin>
			<ymin>59</ymin>
			<xmax>344</xmax>
			<ymax>95</ymax>
		</bndbox>
	</object>
</annotation>
