<annotation>
	<folder>dv51_aps</folder>
	<filename>dv51-0175.bmp</filename>
	<path>F:\data\dv51-40\dv51_aps\dv51-0175.bmp</path>
	<source>
		<database>Unknown</database>
	</source>
	<size>
		<width>346</width>
		<height>260</height>
		<depth>3</depth>
	</size>
	<segmented>0</segmented>
	<object>
		<name>redtail glassfish</name>
		<pose>Unspecified</pose>
		<truncated>0</truncated>
		<difficult>0</difficult>
		<bndbox>
			<xmin>151</xmin>
			<ymin>125</ymin>
			<xmax>233</xmax>
			<ymax>157</ymax>
		</bndbox>
	</object>
	<object>
		<name>redtail glassfish</name>
		<pose>Unspecified</pose>
		<truncated>0</truncated>
		<difficult>0</difficult>
		<bndbox>
			<xmin>268</xmin>
			<ymin>64</ymin>
			<xmax>344</xmax>
			<ymax>120</ymax>
		</bndbox>
	</object>
	<object>
		<name>X-ray fish</name>
		<pose>Unspecified</pose>
		<truncated>1</truncated>
		<difficult>0</difficult>
		<bndbox>
			<xmin>300</xmin>
			<ymin>122</ymin>
			<xmax>346</xmax>
			<ymax>164</ymax>
		</bndbox>
	</object>
</annotation>
