<annotation>
	<folder>dv66_aps</folder>
	<filename>dv66-1295.bmp</filename>
	<path>F:\data\dv66-67\dv66_aps\dv66-1295.bmp</path>
	<source>
		<database>Unknown</database>
	</source>
	<size>
		<width>346</width>
		<height>260</height>
		<depth>3</depth>
	</size>
	<segmented>0</segmented>
	<object>
		<name>moon jellyfish</name>
		<pose>Unspecified</pose>
		<truncated>0</truncated>
		<difficult>0</difficult>
		<bndbox>
			<xmin>16</xmin>
			<ymin>15</ymin>
			<xmax>121</xmax>
			<ymax>93</ymax>
		</bndbox>
	</object>
	<object>
		<name>moon jellyfish</name>
		<pose>Unspecified</pose>
		<truncated>0</truncated>
		<difficult>0</difficult>
		<bndbox>
			<xmin>119</xmin>
			<ymin>6</ymin>
			<xmax>252</xmax>
			<ymax>91</ymax>
		</bndbox>
	</object>
	<object>
		<name>moon jellyfish</name>
		<pose>Unspecified</pose>
		<truncated>0</truncated>
		<difficult>0</difficult>
		<bndbox>
			<xmin>242</xmin>
			<ymin>9</ymin>
			<xmax>329</xmax>
			<ymax>73</ymax>
		</bndbox>
	</object>
</annotation>
