<annotation>
	<folder>dv80_aps</folder>
	<filename>dv80-0755.bmp</filename>
	<path>F:\桌面\jijiji\dv80-77\dv80_aps\dv80-0755.bmp</path>
	<source>
		<database>Unknown</database>
	</source>
	<size>
		<width>346</width>
		<height>260</height>
		<depth>3</depth>
	</size>
	<segmented>0</segmented>
	<object>
		<name>flame jellyfish</name>
		<pose>Unspecified</pose>
		<truncated>0</truncated>
		<difficult>0</difficult>
		<bndbox>
			<xmin>4</xmin>
			<ymin>82</ymin>
			<xmax>60</xmax>
			<ymax>178</ymax>
		</bndbox>
	</object>
	<object>
		<name>flame jellyfish</name>
		<pose>Unspecified</pose>
		<truncated>0</truncated>
		<difficult>0</difficult>
		<bndbox>
			<xmin>5</xmin>
			<ymin>186</ymin>
			<xmax>47</xmax>
			<ymax>233</ymax>
		</bndbox>
	</object>
	<object>
		<name>flame jellyfish</name>
		<pose>Unspecified</pose>
		<truncated>0</truncated>
		<difficult>0</difficult>
		<bndbox>
			<xmin>48</xmin>
			<ymin>187</ymin>
			<xmax>100</xmax>
			<ymax>236</ymax>
		</bndbox>
	</object>
	<object>
		<name>flame jellyfish</name>
		<pose>Unspecified</pose>
		<truncated>1</truncated>
		<difficult>0</difficult>
		<bndbox>
			<xmin>103</xmin>
			<ymin>208</ymin>
			<xmax>181</xmax>
			<ymax>260</ymax>
		</bndbox>
	</object>
</annotation>
