<annotation>
	<folder>dv81_aps</folder>
	<filename>dv81-0040.bmp</filename>
	<path>F:\桌面\jijiji\dv81-41\dv81_aps\dv81-0040.bmp</path>
	<source>
		<database>Unknown</database>
	</source>
	<size>
		<width>346</width>
		<height>260</height>
		<depth>3</depth>
	</size>
	<segmented>0</segmented>
	<object>
		<name>flame jellyfish</name>
		<pose>Unspecified</pose>
		<truncated>0</truncated>
		<difficult>0</difficult>
		<bndbox>
			<xmin>32</xmin>
			<ymin>74</ymin>
			<xmax>76</xmax>
			<ymax>138</ymax>
		</bndbox>
	</object>
	<object>
		<name>flame jellyfish</name>
		<pose>Unspecified</pose>
		<truncated>0</truncated>
		<difficult>0</difficult>
		<bndbox>
			<xmin>191</xmin>
			<ymin>163</ymin>
			<xmax>274</xmax>
			<ymax>232</ymax>
		</bndbox>
	</object>
	<object>
		<name>flame jellyfish</name>
		<pose>Unspecified</pose>
		<truncated>0</truncated>
		<difficult>0</difficult>
		<bndbox>
			<xmin>260</xmin>
			<ymin>155</ymin>
			<xmax>313</xmax>
			<ymax>201</ymax>
		</bndbox>
	</object>
</annotation>
