<annotation>
	<folder>dv91_aps</folder>
	<filename>dv92-0295.bmp</filename>
	<path>F:\桌面\jijiji\dv91-70\dv91_aps\dv92-0295.bmp</path>
	<source>
		<database>Unknown</database>
	</source>
	<size>
		<width>346</width>
		<height>260</height>
		<depth>3</depth>
	</size>
	<segmented>0</segmented>
	<object>
		<name>flame jellyfish</name>
		<pose>Unspecified</pose>
		<truncated>0</truncated>
		<difficult>0</difficult>
		<bndbox>
			<xmin>104</xmin>
			<ymin>185</ymin>
			<xmax>183</xmax>
			<ymax>244</ymax>
		</bndbox>
	</object>
	<object>
		<name>flame jellyfish</name>
		<pose>Unspecified</pose>
		<truncated>0</truncated>
		<difficult>0</difficult>
		<bndbox>
			<xmin>287</xmin>
			<ymin>150</ymin>
			<xmax>342</xmax>
			<ymax>222</ymax>
		</bndbox>
	</object>
	<object>
		<name>flame jellyfish</name>
		<pose>Unspecified</pose>
		<truncated>1</truncated>
		<difficult>0</difficult>
		<bndbox>
			<xmin>1</xmin>
			<ymin>39</ymin>
			<xmax>16</xmax>
			<ymax>83</ymax>
		</bndbox>
	</object>
</annotation>
